[
  {
    "protocol_code": "BREAST-ABEMACICLIB-ANASTROZOLE",
    "protocol_name": "Breast Cancer - Abemaciclib-Anastrozole",
    "disease_site": "Breast",
    "category": "breast",
    "cycle_length_days": 28,
    "number_of_cycles": null,
    "drugs": [
      {
        "drug_name": "Abemaciclib",
        "dose": 150.0,
        "dose_unit": "mg",
        "route": "Oral",
        "days": [
          1,
          2,
          3,
          4,
          5,
          6,
          7,
          8,
          9,
          10,
          11,
          12,
          13,
          14,
          15,
          16,
          17,
          18,
          19,
          20,
          21,
          22,
          23,
          24,
          25,
          26,
          27,
          28
        ],
        "infusion_duration_hours": null,
        "max_dose": null,
        "max_dose_unit": null,
        "notes": "150mg twice daily days 1-28. Dose reductions: first reduction to 100mg twice daily, second reduction to 50mg twice daily. Interacts with CYP3A4 agents - always check interactions. If patient vomits or misses a dose, do not take extra dose that day."
      },
      {
        "drug_name": "Anastrozole",
        "dose": 1.0,
        "dose_unit": "mg",
        "route": "Oral",
        "days": [
          1,
          2,
          3,
          4,
          5,
          6,
          7,
          8,
          9,
          10,
          11,
          12,
          13,
          14,
          15,
          16,
          17,
          18,
          19,
          20,
          21,
          22,
          23,
          24,
          25,
          26,
          27,
          28
        ],
        "infusion_duration_hours": null,
        "max_dose": null,
        "max_dose_unit": null,
        "notes": "1mg once daily days 1-28. No dose reductions required for anastrozole due to myelosuppression."
      }
    ],
    "dose_modifications": [
      {
        "condition": "Haematological toxicity Grade 3",
        "drug_name": "Abemaciclib",
        "factor": 1.0,
        "notes": "Suspend dose until toxicity resolves to NCI grade 2 or less. Dose reduction is not required."
      },
      {
        "condition": "Haematological toxicity Grade 3 recurrent or Grade 4",
        "drug_name": "Abemaciclib",
        "factor": 0.75,
        "notes": "Suspend dose until toxicity resolves to NCI grade 2 or less. Resume at next lower dose level."
      },
      {
        "condition": "Blood cell growth factors required",
        "drug_name": "Abemaciclib",
        "factor": 0.75,
        "notes": "Suspend dose for at least 48 hours after last growth factor dose and until toxicity resolves to NCI grade 2 or less. Resume at next lower dose unless dose was already reduced for that toxicity."
      },
      {
        "condition": "Hepatic toxicity persistent or recurrent Grade 2 or Grade 3 (ALT/AST)",
        "drug_name": "Abemaciclib",
        "factor": 0.75,
        "notes": "Suspend dose until toxicity resolves to baseline or Grade 1. Resume at next lower dose."
      },
      {
        "condition": "Hepatic toxicity Grade 4 (ALT/AST)",
        "drug_name": "Abemaciclib",
        "factor": 0.0,
        "notes": "Discontinue abemaciclib."
      },
      {
        "condition": "Severe renal impairment",
        "drug_name": "Anastrozole",
        "factor": 1.0,
        "notes": "Administer with caution in patients with severe renal impairment."
      },
      {
        "condition": "Severe renal impairment",
        "drug_name": "Abemaciclib",
        "factor": 1.0,
        "notes": "No data for severe renal impairment. Use with caution and close monitoring for signs of toxicity."
      },
      {
        "condition": "Diarrhoea Grade 2 not resolving within 24 hours",
        "drug_name": "Abemaciclib",
        "factor": 1.0,
        "notes": "Suspend dose until resolution. Dose reduction is not required."
      },
      {
        "condition": "Diarrhoea Grade 2 persisting or recurring despite maximal supportive measures, or Grade 3/4",
        "drug_name": "Abemaciclib",
        "factor": 0.75,
        "notes": "Suspend dose until toxicity resolves to Grade 1 or less. Resume at next lower dose."
      },
      {
        "condition": "Non-haematological toxicity (not diarrhoea or liver) persistent or recurrent Grade 2 not resolving within 7 days, or Grade 3/4",
        "drug_name": "Abemaciclib",
        "factor": 0.75,
        "notes": "Suspend dose until toxicity resolves to Grade 1 or less. Resume at next lower dose."
      }
    ],
    "pre_medications": [
      "Loperamide 4mg after first loose stool then 2mg after each subsequent loose stool up to maximum 16mg in 24 hours (take home)"
    ],
    "special_warnings": [
      "CDK4/6 inhibitor: Abemaciclib interacts with many agents especially CYP3A4 inhibitors/inducers - always check drug interactions.",
      "Monitor for hepatotoxicity: LFTs at baseline, every 2 weeks for first 2 months, monthly for next 2 months, then as indicated.",
      "FBC, LFTs and U&Es at baseline then every 2 weeks for first 8 weeks, then every 4 weeks for further 8 weeks, then minimum every 12 weeks.",
      "Treatment breaks of up to 6 weeks allowed to allow toxicities to settle.",
      "In pre- or perimenopausal women, endocrine therapy must be combined with LHRH agonist (not included in ARIA regimen).",
      "If third dose reduction necessary, treatment should be stopped.",
      "Follow National Patient Safety Alert on oral chemotherapy (NPSA/2008/RRR001).",
      "Abemaciclib should only be prescribed under supervision of a consultant oncologist.",
      "Maximum of 12 cycles set in ARIA but treatment continues until disease progression or intolerance."
    ],
    "required_patient_fields": [
      "neutrophil_count",
      "platelet_count",
      "liver_function_tests",
      "renal_function",
      "ecog_performance_status"
    ],
    "auc_dosing": null
  },
  {
    "protocol_code": "BREAST-ABEMACICLIB-FULVESTRANT",
    "protocol_name": "Breast Cancer - Abemaciclib-Fulvestrant",
    "disease_site": "Breast",
    "category": "breast",
    "cycle_length_days": 28,
    "number_of_cycles": null,
    "drugs": [
      {
        "drug_name": "Abemaciclib",
        "dose": 150.0,
        "dose_unit": "mg",
        "route": "Oral",
        "days": [
          1,
          2,
          3,
          4,
          5,
          6,
          7,
          8,
          9,
          10,
          11,
          12,
          13,
          14,
          15,
          16,
          17,
          18,
          19,
          20,
          21,
          22,
          23,
          24,
          25,
          26,
          27,
          28
        ],
        "infusion_duration_hours": null,
        "max_dose": null,
        "max_dose_unit": null,
        "notes": "150mg twice daily days 1-28. Dose reductions: first reduction to 100mg twice daily, second reduction to 50mg twice daily. If patient vomits or misses a dose, do not take extra dose that day."
      },
      {
        "drug_name": "Fulvestrant",
        "dose": 500.0,
        "dose_unit": "mg",
        "route": "Intramuscular",
        "days": [
          1,
          15
        ],
        "infusion_duration_hours": null,
        "max_dose": null,
        "max_dose_unit": null,
        "notes": "Cycle 1: 500mg on days 1 and 15. Cycle 2 onwards: 500mg on day 1 only. Administered as two consecutive 5ml slow IM injections (1-2 min/injection), one in each buttock. Caution at dorsogluteal site due to proximity to sciatic nerve."
      }
    ],
    "dose_modifications": [
      {
        "condition": "Haematological toxicity Grade 3",
        "drug_name": "Abemaciclib",
        "factor": 1.0,
        "notes": "Suspend dose until toxicity resolves to NCI grade 2 or less. Dose reduction is not required."
      },
      {
        "condition": "Haematological toxicity Grade 3 recurrent or Grade 4",
        "drug_name": "Abemaciclib",
        "factor": 0.75,
        "notes": "Suspend dose until toxicity resolves to NCI grade 2 or less. Resume at next lower dose level."
      },
      {
        "condition": "Blood cell growth factors required",
        "drug_name": "Abemaciclib",
        "factor": 0.75,
        "notes": "Suspend dose for at least 48 hours after last growth factor dose and until toxicity resolves to NCI grade 2 or less. Resume at next lower dose unless dose was already reduced."
      },
      {
        "condition": "Hepatic toxicity persistent or recurrent Grade 2 or Grade 3 (ALT/AST)",
        "drug_name": "Abemaciclib",
        "factor": 0.75,
        "notes": "Suspend dose until toxicity resolves to baseline or Grade 1. Resume at next lower dose."
      },
      {
        "condition": "Hepatic toxicity Grade 4 (ALT/AST)",
        "drug_name": "Abemaciclib",
        "factor": 0.0,
        "notes": "Discontinue abemaciclib."
      },
      {
        "condition": "Moderate to severe hepatic impairment",
        "drug_name": "Fulvestrant",
        "factor": 1.0,
        "notes": "Caution advised in moderate to severe hepatic impairment."
      },
      {
        "condition": "Severe renal impairment",
        "drug_name": "Fulvestrant",
        "factor": 1.0,
        "notes": "Administer with caution in severe renal impairment."
      },
      {
        "condition": "Severe renal impairment",
        "drug_name": "Abemaciclib",
        "factor": 1.0,
        "notes": "No data for severe renal impairment. Use with caution and close monitoring."
      },
      {
        "condition": "Diarrhoea Grade 2 not resolving within 24 hours",
        "drug_name": "Abemaciclib",
        "factor": 1.0,
        "notes": "Suspend dose until resolution. Dose reduction not required."
      },
      {
        "condition": "Diarrhoea Grade 2 persisting or recurring despite maximal supportive measures, or Grade 3/4",
        "drug_name": "Abemaciclib",
        "factor": 0.75,
        "notes": "Suspend dose until toxicity resolves to Grade 1 or less. Resume at next lower dose."
      },
      {
        "condition": "Non-haematological toxicity persistent or recurrent Grade 2 not resolving within 7 days, or Grade 3/4",
        "drug_name": "Abemaciclib",
        "factor": 0.75,
        "notes": "Suspend dose until toxicity resolves to Grade 1 or less. Resume at next lower dose."
      }
    ],
    "pre_medications": [
      "Loperamide 4mg after first loose stool then 2mg after each subsequent loose stool up to maximum 16mg in 24 hours (take home, day 1 only)"
    ],
    "special_warnings": [
      "CDK4/6 inhibitor: Abemaciclib interacts with many agents especially CYP3A4 - always check drug interactions.",
      "Monitor for hepatotoxicity: LFTs at baseline, every 2 weeks for first 2 months, monthly for next 2 months, then as indicated.",
      "FBC, LFTs and U&Es at baseline then every 2 weeks for first 8 weeks, then every 4 weeks for further 8 weeks, then minimum every 12 weeks.",
      "Treatment breaks of up to 6 weeks allowed solely to allow toxicities to settle.",
      "In pre- or perimenopausal women, ovarian ablation or suppression with LHRH agonist is mandatory (not included in ARIA regimen).",
      "Cycle 1 fulvestrant given on days 1 AND 15; from cycle 2 onwards given on day 1 only.",
      "If third dose reduction necessary, treatment should be stopped.",
      "Follow National Patient Safety Alert on oral chemotherapy (NPSA/2008/RRR001).",
      "Abemaciclib should only be prescribed under supervision of a consultant oncologist.",
      "Maximum of 12 cycles set in ARIA but treatment continues until disease progression or intolerance."
    ],
    "required_patient_fields": [
      "neutrophil_count",
      "platelet_count",
      "liver_function_tests",
      "renal_function",
      "ecog_performance_status"
    ],
    "auc_dosing": null
  },
  {
    "protocol_code": "BREAST-ABEMACICLIB-LETROZOLE",
    "protocol_name": "Breast Cancer - Abemaciclib-Letrozole",
    "disease_site": "Breast",
    "category": "breast",
    "cycle_length_days": 28,
    "number_of_cycles": null,
    "drugs": [
      {
        "drug_name": "Abemaciclib",
        "dose": 150.0,
        "dose_unit": "mg",
        "route": "Oral",
        "days": [
          1,
          2,
          3,
          4,
          5,
          6,
          7,
          8,
          9,
          10,
          11,
          12,
          13,
          14,
          15,
          16,
          17,
          18,
          19,
          20,
          21,
          22,
          23,
          24,
          25,
          26,
          27,
          28
        ],
        "infusion_duration_hours": null,
        "max_dose": null,
        "max_dose_unit": null,
        "notes": "150mg twice daily days 1-28. Dose reductions: first reduction to 100mg twice daily, second reduction to 50mg twice daily. If patient vomits or misses a dose, do not take extra dose that day."
      },
      {
        "drug_name": "Letrozole",
        "dose": 2.5,
        "dose_unit": "mg",
        "route": "Oral",
        "days": [
          1,
          2,
          3,
          4,
          5,
          6,
          7,
          8,
          9,
          10,
          11,
          12,
          13,
          14,
          15,
          16,
          17,
          18,
          19,
          20,
          21,
          22,
          23,
          24,
          25,
          26,
          27,
          28
        ],
        "infusion_duration_hours": null,
        "max_dose": null,
        "max_dose_unit": null,
        "notes": "2.5mg once daily days 1-28. No dose reductions required for letrozole due to myelosuppression."
      }
    ],
    "dose_modifications": [
      {
        "condition": "Haematological toxicity Grade 3",
        "drug_name": "Abemaciclib",
        "factor": 1.0,
        "notes": "Suspend dose until toxicity resolves to NCI grade 2 or less. Dose reduction is not required."
      },
      {
        "condition": "Haematological toxicity Grade 3 recurrent or Grade 4",
        "drug_name": "Abemaciclib",
        "factor": 0.75,
        "notes": "Suspend dose until toxicity resolves to NCI grade 2 or less. Resume at next lower dose level."
      },
      {
        "condition": "Blood cell growth factors required",
        "drug_name": "Abemaciclib",
        "factor": 0.75,
        "notes": "Suspend dose for at least 48 hours after last growth factor dose and until toxicity resolves to NCI grade 2 or less. Resume at next lower dose unless dose was already reduced."
      },
      {
        "condition": "Hepatic toxicity persistent or recurrent Grade 2 or Grade 3 (ALT/AST)",
        "drug_name": "Abemaciclib",
        "factor": 0.75,
        "notes": "Suspend dose until toxicity resolves to baseline or Grade 1. Resume at next lower dose."
      },
      {
        "condition": "Hepatic toxicity Grade 4 (ALT/AST)",
        "drug_name": "Abemaciclib",
        "factor": 0.0,
        "notes": "Discontinue abemaciclib."
      },
      {
        "condition": "Moderate to severe hepatic impairment",
        "drug_name": "Letrozole",
        "factor": 1.0,
        "notes": "Caution advised in moderate to severe hepatic impairment."
      },
      {
        "condition": "Severe renal impairment",
        "drug_name": "Letrozole",
        "factor": 1.0,
        "notes": "Administer letrozole with caution in severe renal impairment."
      },
      {
        "condition": "Severe renal impairment",
        "drug_name": "Abemaciclib",
        "factor": 1.0,
        "notes": "No data for severe renal impairment. Use with caution and close monitoring."
      },
      {
        "condition": "Diarrhoea Grade 2 not resolving within 24 hours",
        "drug_name": "Abemaciclib",
        "factor": 1.0,
        "notes": "Suspend dose until resolution. Dose reduction not required."
      },
      {
        "condition": "Diarrhoea Grade 2 persisting or recurring despite maximal supportive measures, or Grade 3/4",
        "drug_name": "Abemaciclib",
        "factor": 0.75,
        "notes": "Suspend dose until toxicity resolves to Grade 1 or less. Resume at next lower dose."
      },
      {
        "condition": "Non-haematological toxicity persistent or recurrent Grade 2 not resolving within 7 days, or Grade 3/4",
        "drug_name": "Abemaciclib",
        "factor": 0.75,
        "notes": "Suspend dose until toxicity resolves to Grade 1 or less. Resume at next lower dose."
      }
    ],
    "pre_medications": [
      "Loperamide 4mg after first loose stool then 2mg after each subsequent loose stool up to maximum 16mg in 24 hours (take home)"
    ],
    "special_warnings": [
      "CDK4/6 inhibitor: Abemaciclib interacts with many agents especially CYP3A4 - always check drug interactions.",
      "Monitor for hepatotoxicity: LFTs at baseline, every 2 weeks for first 2 months, monthly for next 2 months, then as indicated.",
      "FBC, LFTs and U&Es at baseline then every 2 weeks for first 8 weeks, then every 4 weeks for further 8 weeks, then minimum every 12 weeks.",
      "Treatment breaks of up to 6 weeks allowed solely to allow toxicities to settle.",
      "In pre- or perimenopausal women, endocrine therapy must be combined with LHRH agonist (not included in ARIA regimen).",
      "If third dose reduction necessary, treatment should be stopped.",
      "Follow National Patient Safety Alert on oral chemotherapy (NPSA/2008/RRR001).",
      "Abemaciclib should only be prescribed under supervision of a consultant oncologist.",
      "Maximum of 12 cycles set in ARIA but treatment continues until disease progression or intolerance."
    ],
    "required_patient_fields": [
      "neutrophil_count",
      "platelet_count",
      "liver_function_tests",
      "renal_function",
      "ecog_performance_status"
    ],
    "auc_dosing": null
  },
  {
    "protocol_code": "BREAST-CEP-ACCELERATED-14",
    "protocol_name": "Breast Cancer - Cyclophosphamide-Epirubicin-Paclitaxel (Accelerated, 14-day)",
    "disease_site": "Breast",
    "category": "breast",
    "cycle_length_days": 14,
    "number_of_cycles": 8,
    "drugs": [
      {
        "drug_name": "Cyclophosphamide",
        "dose": 600.0,
        "dose_unit": "mg/m²",
        "route": "IV bolus",
        "days": [
          1
        ],
        "infusion_duration_hours": 0.167,
        "max_dose": null,
        "max_dose_unit": null,
        "notes": "Cycles 1-4 only (Phase 1). Intravenous bolus over 10 minutes. Dose banded per national dose bands (20mg/mL). Reduce to 75% if CrCl 10-20ml/min; 50% if CrCl <10ml/min."
      },
      {
        "drug_name": "Epirubicin",
        "dose": 90.0,
        "dose_unit": "mg/m²",
        "route": "IV bolus",
        "days": [
          1
        ],
        "infusion_duration_hours": 0.167,
        "max_dose": null,
        "max_dose_unit": null,
        "notes": "Cycles 1-4 only (Phase 1). Intravenous bolus over 10 minutes. Dose banded per national dose bands (2mg/mL). Maximum cumulative lifetime dose 900mg/m². Vesicant - follow extravasation protocol. Discontinue if cardiac failure develops."
      },
      {
        "drug_name": "Paclitaxel",
        "dose": 175.0,
        "dose_unit": "mg/m²",
        "route": "IV infusion",
        "days": [
          1
        ],
        "infusion_duration_hours": 3.0,
        "max_dose": null,
        "max_dose_unit": null,
        "notes": "Cycles 5-8 only (Phase 2). IV infusion in 500ml sodium chloride 0.9% over 180 minutes. Must be administered via non-PVC set with in-line 0.22 micron filter. Dose banded (6mg/mL). Vesicant. Blood pressure and pulse monitored half-hourly during infusion. Hepatic dose reductions: bilirubin <26 umol/L = 135mg/m²; 27-51 umol/L = 75mg/m²; >51 umol/L = 50mg/m²."
      }
    ],
    "dose_modifications": [
      {
        "condition": "Haematological Grade 3 or above event",
        "drug_name": "Cyclophosphamide",
        "factor": 0.8,
        "notes": "Reduce to 80% of original dose after NCI-CTC grade 3+ haematological event. If second episode despite dose reduction, consider changing or stopping therapy."
      },
      {
        "condition": "Haematological Grade 3 or above event",
        "drug_name": "Epirubicin",
        "factor": 0.8,
        "notes": "Reduce to 80% of original dose after NCI-CTC grade 3+ haematological event."
      },
      {
        "condition": "Haematological Grade 3 or above event",
        "drug_name": "Paclitaxel",
        "factor": 0.8,
        "notes": "Reduce to 80% of original dose after NCI-CTC grade 3+ haematological event."
      },
      {
        "condition": "Renal impairment CrCl 10-20 ml/min",
        "drug_name": "Cyclophosphamide",
        "factor": 0.75,
        "notes": "Reduce to 75% of original dose."
      },
      {
        "condition": "Renal impairment CrCl <10 ml/min",
        "drug_name": "Cyclophosphamide",
        "factor": 0.5,
        "notes": "Reduce to 50% of original dose."
      },
      {
        "condition": "Severe renal impairment",
        "drug_name": "Epirubicin",
        "factor": 0.75,
        "notes": "Dose reduce in severe impairment only."
      },
      {
        "condition": "Hepatic impairment bilirubin 24-51 umol/L",
        "drug_name": "Epirubicin",
        "factor": 0.5,
        "notes": "Give 50% of original dose. Also applies if AST 2-4x ULN or bilirubin 21-51 umol/L."
      },
      {
        "condition": "Hepatic impairment bilirubin 52-85 umol/L",
        "drug_name": "Epirubicin",
        "factor": 0.25,
        "notes": "Give 25% of original dose. Also applies if AST >4x ULN or bilirubin >51 umol/L."
      },
      {
        "condition": "Hepatic impairment bilirubin >=85 umol/L",
        "drug_name": "Epirubicin",
        "factor": 0.0,
        "notes": "Contra-indicated."
      },
      {
        "condition": "Peripheral neuropathy NCI-CTC Grade 2",
        "drug_name": "Paclitaxel",
        "factor": 0.75,
        "notes": "Withhold paclitaxel until neuropathy recovers to NCI-CTC grade 1 then reduce to 75% of original dose."
      },
      {
        "condition": "Peripheral neuropathy NCI-CTC Grade 3",
        "drug_name": "Paclitaxel",
        "factor": 0.5,
        "notes": "Withhold until resolves to NCI-CTC grade 1 then reduce to 50% of original dose. Discontinue if neuropathy does not resolve to grade 1."
      }
    ],
    "pre_medications": [
      "Dexamethasone 8mg oral or IV 15-30 minutes prior to cyclophosphamide/epirubicin (cycles 1-4)",
      "Ondansetron 8mg oral or IV 15-30 minutes prior to cyclophosphamide/epirubicin (cycles 1-4)",
      "Dexamethasone 4mg twice daily oral for 3 days starting day 2 of cycle (take home, cycles 1-4)",
      "Metoclopramide 10mg three times daily when required oral (take home, cycles 1-4)",
      "Ondansetron 8mg twice daily oral for 3 days starting evening of day 1 (take home, cycles 1-4)",
      "Chlorphenamine 10mg IV 30 minutes prior to paclitaxel (cycles 5-8)",
      "Dexamethasone 20mg IV 30 minutes prior to paclitaxel (cycles 5-8)",
      "H2 antagonist per local formulary 30 minutes prior to paclitaxel (cycles 5-8): ranitidine 50mg IV or famotidine 20mg oral or nizatidine 150mg oral or ranitidine 150mg oral",
      "Metoclopramide 10mg oral or IV 15-30 minutes prior to paclitaxel (cycles 5-8)",
      "Metoclopramide 10mg three times daily when required oral (take home, cycles 5-8)",
      "G-CSF: filgrastim 30MU SC daily for 5 days from day 3, OR lenograstim 33.6MU SC daily for 5 days from day 3, OR pegfilgrastim/lipegfilgrastim 6mg SC on day 2 (all cycles)"
    ],
    "special_warnings": [
      "Regimen is two sequential phases: Cyclophosphamide + Epirubicin x4 cycles (14-day), THEN Paclitaxel x4 cycles (14-day). Total 8 cycles.",
      "Epirubicin: maximum cumulative lifetime dose is 900mg/m². Monitor LVEF at baseline especially in patients with cardiac history.",
      "Ensure adequate cardiac function before starting epirubicin. Discontinue if cardiac failure develops.",
      "Epirubicin is a vesicant - follow extravasation guidelines.",
      "Paclitaxel is a vesicant - follow extravasation guidelines.",
      "Paclitaxel must be administered via non-PVC administration set with in-line 0.22 micron filter.",
      "Hypersensitivity reactions to paclitaxel tend to occur with first or second infusion. Interrupt for minor symptoms; immediately discontinue for severe reactions (profound hypotension, bronchospasm, generalised erythema).",
      "Blood pressure and pulse monitored half-hourly during paclitaxel infusion.",
      "Growth factors (G-CSF) required for all cycles due to accelerated schedule.",
      "Baseline LVEF measurement required."
    ],
    "required_patient_fields": [
      "neutrophil_count",
      "platelet_count",
      "liver_function_tests",
      "creatinine_clearance",
      "lvef"
    ],
    "auc_dosing": null
  },
  {
    "protocol_code": "BREAST-ANASTROZOLE-PALBOCICLIB",
    "protocol_name": "Breast Cancer - Anastrozole-Palbociclib",
    "disease_site": "Breast",
    "category": "breast",
    "cycle_length_days": 28,
    "number_of_cycles": null,
    "drugs": [
      {
        "drug_name": "Anastrozole",
        "dose": 1.0,
        "dose_unit": "mg",
        "route": "Oral",
        "days": [
          1,
          2,
          3,
          4,
          5,
          6,
          7,
          8,
          9,
          10,
          11,
          12,
          13,
          14,
          15,
          16,
          17,
          18,
          19,
          20,
          21,
          22,
          23,
          24,
          25,
          26,
          27,
          28
        ],
        "infusion_duration_hours": null,
        "max_dose": null,
        "max_dose_unit": null,
        "notes": "1mg once daily days 1-28. No dose reductions required for anastrozole due to myelosuppression."
      },
      {
        "drug_name": "Palbociclib",
        "dose": 125.0,
        "dose_unit": "mg",
        "route": "Oral",
        "days": [
          1,
          2,
          3,
          4,
          5,
          6,
          7,
          8,
          9,
          10,
          11,
          12,
          13,
          14,
          15,
          16,
          17,
          18,
          19,
          20,
          21
        ],
        "infusion_duration_hours": null,
        "max_dose": null,
        "max_dose_unit": null,
        "notes": "125mg once daily days 1-21, then 7 days off. Dose reductions: level -1 = 100mg/day, level -2 = 75mg/day. Must be taken with food. Swallow capsules whole, do not chew. If vomit or miss dose, do not take extra dose."
      }
    ],
    "dose_modifications": [
      {
        "condition": "Haematological toxicity Grade 1 or 2",
        "drug_name": "Palbociclib",
        "factor": 1.0,
        "notes": "No change."
      },
      {
        "condition": "Haematological toxicity Grade 3 on Day 1",
        "drug_name": "Palbociclib",
        "factor": 1.0,
        "notes": "Delay one week. When recovered to NCI-CTC grade 2 or below restart at same dose. Consider dose reduction if recovery takes 7 days or longer or recurrent grade 3 neutropenia."
      },
      {
        "condition": "Haematological toxicity Grade 3 with fever",
        "drug_name": "Palbociclib",
        "factor": 0.75,
        "notes": "Delay until recovery to NCI-CTC grade 2 or below. Restart at next lower dose level."
      },
      {
        "condition": "Haematological toxicity Grade 4",
        "drug_name": "Palbociclib",
        "factor": 0.75,
        "notes": "Delay until recovery to NCI-CTC grade 2 or below. Restart at next lower dose level."
      },
      {
        "condition": "Non-haematological toxicity Grade 3 or 4",
        "drug_name": "Palbociclib",
        "factor": 0.75,
        "notes": "Delay until recovery to NCI-CTC grade 2 or below. Restart at next lower dose level."
      },
      {
        "condition": "Severe renal impairment CrCl <30 ml/min",
        "drug_name": "Palbociclib",
        "factor": 1.0,
        "notes": "Insufficient data. Administer only after careful consideration of benefits/risks with close monitoring."
      },
      {
        "condition": "Moderate or severe hepatic impairment (bilirubin >1.5x ULN and any AST)",
        "drug_name": "Palbociclib",
        "factor": 1.0,
        "notes": "Insufficient data. Administer only after careful consideration of benefits/risks with close monitoring."
      }
    ],
    "pre_medications": [],
    "special_warnings": [
      "CDK4/6 inhibitor: Palbociclib interacts with many other agents - always check drug interactions.",
      "FBC, LFTs and U&Es at baseline then day 1 of each cycle. For cycles 1 and 2, FBC also on day 14.",
      "Neutropenia most frequent adverse effect: median onset 15 days (any grade), 28 days (grade 3/4). Median duration of severe neutropenia 7 days.",
      "Increased risk of infection vs aromatase inhibitor alone - warn patients to report fever promptly.",
      "Treatment breaks up to 6 weeks allowed solely to allow toxicities to settle.",
      "In pre- or perimenopausal women, ovarian ablation or suppression with LHRH agonist is mandatory (not included in ARIA regimen).",
      "If third dose reduction necessary, treatment should be stopped.",
      "Follow National Patient Safety Alert on oral chemotherapy (NPSA/2008/RRR001).",
      "Palbociclib should only be prescribed under supervision of a consultant oncologist.",
      "Maximum of 12 cycles set in ARIA but treatment continues until disease progression or intolerance."
    ],
    "required_patient_fields": [
      "neutrophil_count",
      "platelet_count",
      "liver_function_tests",
      "renal_function",
      "ecog_performance_status"
    ],
    "auc_dosing": null
  },
  {
    "protocol_code": "BREAST-ANASTROZOLE-RIBOCICLIB",
    "protocol_name": "Breast Cancer - Anastrozole-Ribociclib",
    "disease_site": "Breast",
    "category": "breast",
    "cycle_length_days": 28,
    "number_of_cycles": null,
    "drugs": [
      {
        "drug_name": "Anastrozole",
        "dose": 1.0,
        "dose_unit": "mg",
        "route": "Oral",
        "days": [
          1,
          2,
          3,
          4,
          5,
          6,
          7,
          8,
          9,
          10,
          11,
          12,
          13,
          14,
          15,
          16,
          17,
          18,
          19,
          20,
          21,
          22,
          23,
          24,
          25,
          26,
          27,
          28
        ],
        "infusion_duration_hours": null,
        "max_dose": null,
        "max_dose_unit": null,
        "notes": "1mg once daily days 1-28. No dose reductions required for anastrozole due to myelosuppression."
      },
      {
        "drug_name": "Ribociclib",
        "dose": 600.0,
        "dose_unit": "mg",
        "route": "Oral",
        "days": [
          1,
          2,
          3,
          4,
          5,
          6,
          7,
          8,
          9,
          10,
          11,
          12,
          13,
          14,
          15,
          16,
          17,
          18,
          19,
          20,
          21
        ],
        "infusion_duration_hours": null,
        "max_dose": null,
        "max_dose_unit": null,
        "notes": "600mg once daily days 1-21, then 7 days off. Dose reductions: level -1 = 400mg/day, level -2 = 200mg/day. Discontinue if 200mg dose not tolerated. Can be taken with or without food. If vomit or miss dose, do not take extra."
      }
    ],
    "dose_modifications": [
      {
        "condition": "Haematological toxicity Grade 1 or 2",
        "drug_name": "Ribociclib",
        "factor": 1.0,
        "notes": "No change."
      },
      {
        "condition": "Haematological toxicity Grade 3 on Day 1",
        "drug_name": "Ribociclib",
        "factor": 1.0,
        "notes": "Delay one week. When recovered to NCI-CTC grade 2 or below restart at same dose. Consider dose reduction if recovery takes 7 days or longer or recurrent grade 3 neutropenia in subsequent cycles."
      },
      {
        "condition": "Haematological toxicity Grade 3 with fever",
        "drug_name": "Ribociclib",
        "factor": 0.75,
        "notes": "Delay until recovery to NCI-CTC grade 2 or below. Restart at next lower dose level."
      },
      {
        "condition": "Haematological toxicity Grade 4",
        "drug_name": "Ribociclib",
        "factor": 0.75,
        "notes": "Delay until recovery to NCI-CTC grade 2 or below. Restart at next lower dose level."
      },
      {
        "condition": "Hepatic impairment NCI-CTC Grade 3 (ALT/AST)",
        "drug_name": "Ribociclib",
        "factor": 1.0,
        "notes": "Delay treatment until recovery to NCI-CTC grade 2 or below, then resume at same dose level. If grade 2 recurs, resume at lower dose level."
      },
      {
        "condition": "Hepatic impairment NCI-CTC Grade 4 (ALT/AST)",
        "drug_name": "Ribociclib",
        "factor": 0.75,
        "notes": "Interrupt dose until recovery to NCI-CTC grade 2 or below then resume at next lowest dose level. Discontinue if NCI-CTC toxicity recurs."
      },
      {
        "condition": "ALT/AST >3x ULN combined with total bilirubin >2x ULN",
        "drug_name": "Ribociclib",
        "factor": 0.0,
        "notes": "Discontinue ribociclib irrespective of baseline grade."
      },
      {
        "condition": "Non-haematological or cardiac toxicity NCI-CTC Grade 3",
        "drug_name": "Ribociclib",
        "factor": 1.0,
        "notes": "Dose interruption until recovery to NCI-CTC grade 1 or below, then resume at same dose level. If grade 3 recurs, resume at next lower dose level."
      },
      {
        "condition": "Non-haematological or cardiac toxicity NCI-CTC Grade 4",
        "drug_name": "Ribociclib",
        "factor": 0.0,
        "notes": "Discontinue ribociclib."
      },
      {
        "condition": "QTcF >480msec on ECG",
        "drug_name": "Ribociclib",
        "factor": 1.0,
        "notes": "Interrupt dose. If resolves to <481msec, resume at same dose. If QTcF >=481msec recurs, interrupt until <481msec then resume at next lower dose level."
      },
      {
        "condition": "QTcF >500msec on at least 2 separate ECGs",
        "drug_name": "Ribociclib",
        "factor": 0.75,
        "notes": "Interrupt ribociclib until QTcF <481msec then resume at next lower dose. If QTcF >500msec or >60msec change from baseline with torsade de pointes or polymorphic VT or serious arrhythmia, permanently discontinue."
      },
      {
        "condition": "Severe renal impairment CrCl <30 ml/min",
        "drug_name": "Ribociclib",
        "factor": 1.0,
        "notes": "Insufficient data. Administer only after careful consideration of benefits/risks with close monitoring."
      }
    ],
    "pre_medications": [],
    "special_warnings": [
      "CDK4/6 inhibitor: Ribociclib requires QTc monitoring - ECG before initiating treatment, repeated at day 14 of cycle 1, at beginning of cycle 2, then as clinically indicated.",
      "QTcF prolongation is a known risk with ribociclib - more frequent ECG monitoring required if QTcF prolongation occurs during treatment.",
      "Monitor for hepatotoxicity: FBC and LFTs at baseline and day 1/14 for cycles 1-2, then day 1 of each cycle.",
      "Ribociclib interacts with many other agents - always check drug interactions.",
      "Increased risk of infection vs aromatase inhibitor alone - warn patients to report fever promptly.",
      "Treatment breaks up to 6 weeks allowed solely to allow toxicities to settle.",
      "In pre- or perimenopausal women, ovarian ablation or suppression with LHRH agonist is mandatory (not included in ARIA regimen).",
      "Discontinue ribociclib if the 200mg dose level is not tolerated.",
      "If third dose reduction necessary, treatment should be stopped.",
      "Follow National Patient Safety Alert on oral chemotherapy (NPSA/2008/RRR001).",
      "Ribociclib should only be prescribed under supervision of a consultant oncologist.",
      "Maximum of 12 cycles set in ARIA but treatment continues until disease progression or intolerance."
    ],
    "required_patient_fields": [
      "neutrophil_count",
      "platelet_count",
      "liver_function_tests",
      "renal_function",
      "ecog_performance_status",
      "ecg_qtcf"
    ],
    "auc_dosing": null
  },
  {
    "protocol_code": "BREAST-ATEZOLIZUMAB-NAB-PACLITAXEL",
    "protocol_name": "Breast Cancer - Atezolizumab-Paclitaxel Albumin Bound (Nab-Paclitaxel)",
    "disease_site": "Breast",
    "category": "breast",
    "cycle_length_days": 28,
    "number_of_cycles": null,
    "drugs": [
      {
        "drug_name": "Atezolizumab",
        "dose": 840.0,
        "dose_unit": "mg",
        "route": "IV infusion",
        "days": [
          1,
          15
        ],
        "infusion_duration_hours": 1.0,
        "max_dose": null,
        "max_dose_unit": null,
        "notes": "840mg IV in 100ml sodium chloride 0.9% over 60 minutes on days 1 and 15. First infusion over 60 minutes; if well tolerated subsequent infusions can be over 30 minutes. No dose reductions permitted - delay or discontinue only. Ensure patient receives atezolizumab Patient Alert Card."
      },
      {
        "drug_name": "Paclitaxel albumin bound",
        "dose": 100.0,
        "dose_unit": "mg/m²",
        "route": "IV infusion",
        "days": [
          1,
          8,
          15
        ],
        "infusion_duration_hours": 0.5,
        "max_dose": null,
        "max_dose_unit": null,
        "notes": "100mg/m² IV infusion over 30 minutes on days 1, 8, 15. Dose banded per national dose bands (paclitaxel albumin). Administer using infusion set with 15 micron filter (NOT <15 micron as this may block). NOT interchangeable with standard paclitaxel. Dose level reductions: full=100mg/m², 1st reduction=75mg/m², 2nd reduction=50mg/m², if further reduction needed=discontinue."
      }
    ],
    "dose_modifications": [
      {
        "condition": "Atezolizumab: no dose reductions permitted",
        "drug_name": "Atezolizumab",
        "factor": 1.0,
        "notes": "In principle no dose reductions recommended for atezolizumab. Preference is to delay the dose or discontinue treatment."
      },
      {
        "condition": "Grade 2 pneumonitis (immune-related)",
        "drug_name": "Atezolizumab",
        "factor": 1.0,
        "notes": "Withhold until symptoms resolve and radiographic abnormalities improve. May resume if improves to grade 0-1 within 12 weeks and corticosteroids reduced to <=10mg oral prednisone equivalent/day."
      },
      {
        "condition": "Grade 3 or 4 pneumonitis (immune-related)",
        "drug_name": "Atezolizumab",
        "factor": 0.0,
        "notes": "Permanently discontinue atezolizumab. Consider corticosteroids."
      },
      {
        "condition": "Grade 2-3 diarrhoea or symptomatic colitis (immune-related)",
        "drug_name": "Atezolizumab",
        "factor": 1.0,
        "notes": "Withhold atezolizumab. May resume if improves to grade 0-1 within 12 weeks and corticosteroids reduced to <=10mg/day."
      },
      {
        "condition": "Grade 4 diarrhoea or colitis (immune-related)",
        "drug_name": "Atezolizumab",
        "factor": 0.0,
        "notes": "Permanently discontinue atezolizumab."
      },
      {
        "condition": "Grade 3-4 serum amylase/lipase or Grade 2-3 pancreatitis (immune-related)",
        "drug_name": "Atezolizumab",
        "factor": 1.0,
        "notes": "Withhold atezolizumab. May resume if improves to grade 0-1 within 12 weeks and corticosteroids tapered."
      },
      {
        "condition": "Grade 4 or recurrent pancreatitis (immune-related)",
        "drug_name": "Atezolizumab",
        "factor": 0.0,
        "notes": "Permanently discontinue atezolizumab."
      },
      {
        "condition": "Grade 2 hepatitis (ALT/AST 3-5x ULN or bilirubin 1.5-3x ULN) persisting 5-7 days",
        "drug_name": "Atezolizumab",
        "factor": 1.0,
        "notes": "Withhold and consider corticosteroid. May resume when improves to grade 1 or below within 12 weeks."
      },
      {
        "condition": "Grade 3 or above hepatitis (ALT/AST >5x ULN or bilirubin >3x ULN)",
        "drug_name": "Atezolizumab",
        "factor": 0.0,
        "notes": "Permanently discontinue atezolizumab."
      },
      {
        "condition": "Symptomatic immune-related thyroid disorders",
        "drug_name": "Atezolizumab",
        "factor": 1.0,
        "notes": "Withhold atezolizumab. Resume when symptoms controlled with thyroid replacement/cabimazole."
      },
      {
        "condition": "Immune-related myasthenic syndrome/myasthenia gravis/Guillain-Barre/meningoencephalitis (all grades)",
        "drug_name": "Atezolizumab",
        "factor": 0.0,
        "notes": "Permanently discontinue atezolizumab."
      },
      {
        "condition": "Grade 3-4 rash (immune-related)",
        "drug_name": "Atezolizumab",
        "factor": 1.0,
        "notes": "Withhold atezolizumab. Grade 3: may resume if resolved and corticosteroids reduced. Grade 4: permanently discontinue."
      },
      {
        "condition": "Grade 4 rash (immune-related)",
        "drug_name": "Atezolizumab",
        "factor": 0.0,
        "notes": "Permanently discontinue atezolizumab."
      },
      {
        "condition": "Hepatic impairment moderate to severe (bilirubin 1.5-5x ULN, AST <=10x ULN) - metastatic BC",
        "drug_name": "Paclitaxel albumin bound",
        "factor": 0.8,
        "notes": "20% dose reduction recommended for moderate to severe hepatic impairment in metastatic breast cancer."
      },
      {
        "condition": "Febrile neutropenia NCI-CTC grade 3-4",
        "drug_name": "Paclitaxel albumin bound",
        "factor": 0.75,
        "notes": "Withhold until fever resolves and neutrophil count >=1.5x10^9/L, then resume at next lower dose level."
      },
      {
        "condition": "Peripheral neuropathy NCI-CTC grade 3-4",
        "drug_name": "Paclitaxel albumin bound",
        "factor": 0.75,
        "notes": "Withhold until improves to NCI-CTC grade 1 or below, then resume at next lower dose level."
      },
      {
        "condition": "Cutaneous toxicity NCI-CTC grade 2-3",
        "drug_name": "Paclitaxel albumin bound",
        "factor": 0.75,
        "notes": "Reduce to next lower dose level. Discontinue if adverse drug reaction persists."
      },
      {
        "condition": "Gastrointestinal toxicity grade 3 mucositis or diarrhoea",
        "drug_name": "Paclitaxel albumin bound",
        "factor": 0.75,
        "notes": "Withhold until improves to NCI-CTC grade 1 or below, then resume at next lower dose level."
      }
    ],
    "pre_medications": [
      "Metoclopramide 10mg oral or IV 15-30 minutes prior to chemotherapy on days 1, 8, 15",
      "Metoclopramide 10mg three times daily when required oral (take home, day 1 only)",
      "Chlorphenamine 10mg IV when required for infusion related reactions on days 1 and 15",
      "Hydrocortisone sodium succinate 100mg IV when required for infusion related reactions on days 1 and 15",
      "Paracetamol 1000mg oral when required for infusion related reactions on days 1 and 15",
      "Loperamide 4mg oral initially then 2mg after each loose stool up to maximum 16mg/24 hours when required"
    ],
    "special_warnings": [
      "Paclitaxel albumin bound (Abraxane/nab-paclitaxel) is NOT interchangeable with standard (solvent-based) paclitaxel - different doses, schedules, and toxicity profiles.",
      "IMMUNOTHERAPY: Atezolizumab dose reductions are NOT permitted. Preference is to delay or discontinue only.",
      "Immune-related adverse reactions can be severe or life-threatening and may involve GI, liver, skin, nervous, endocrine, or other organ systems.",
      "Atezolizumab should be permanently discontinued for: NCI-CTC grade 3-4 pneumonitis or hepatitis; any other life-threatening NCI-CTC grade 4 reaction including colitis and renal impairment; any recurrence of severe or NCI-CTC grade 3 reaction; any persistent NCI-CTC grade 2-3 treatment-related adverse reaction that does not recover to grade 1 or resolve within 12 weeks.",
      "Systemic corticosteroids should be avoided before starting atezolizumab (may interfere with efficacy), but can be used after starting to treat immune-related reactions.",
      "Thyroid function tests required prior to starting treatment and every 6 weeks or if clinically indicated.",
      "Treatment breaks of up to 12 weeks beyond expected 3-weekly cycle length allowed to settle immune toxicities.",
      "Formal medical review scheduled at least by end of first 8 weeks of treatment.",
      "Patients must be given an atezolizumab Patient Alert Card.",
      "FBC, LFTs and U&Es prior to days 1, 8, 15 of each cycle.",
      "Administer paclitaxel albumin bound using infusion set incorporating a 15 micron filter (filters <15 micron may block).",
      "Do not use medical devices containing silicone oil (syringes and IV bags) to administer paclitaxel albumin bound."
    ],
    "required_patient_fields": [
      "neutrophil_count",
      "platelet_count",
      "liver_function_tests",
      "renal_function",
      "pd_l1_status",
      "thyroid_function_tests"
    ],
    "auc_dosing": null
  },
  {
    "protocol_code": "BREAST-TAC",
    "protocol_name": "Breast Cancer - Cyclophosphamide-Docetaxel-Doxorubicin (TAC)",
    "disease_site": "Breast",
    "category": "breast",
    "cycle_length_days": 21,
    "number_of_cycles": 6,
    "drugs": [
      {
        "drug_name": "Doxorubicin",
        "dose": 50.0,
        "dose_unit": "mg/m²",
        "route": "IV bolus",
        "days": [
          1
        ],
        "infusion_duration_hours": 0.167,
        "max_dose": null,
        "max_dose_unit": null,
        "notes": "50mg/m² IV bolus over 10 minutes on day 1. Dose banded per CSCCN agreed bands. Maximum cumulative lifetime dose 450mg/m². Vesicant - follow extravasation protocol. Discontinue if cardiac failure develops."
      },
      {
        "drug_name": "Docetaxel",
        "dose": 75.0,
        "dose_unit": "mg/m²",
        "route": "IV infusion",
        "days": [
          1
        ],
        "infusion_duration_hours": 1.0,
        "max_dose": null,
        "max_dose_unit": null,
        "notes": "75mg/m² IV infusion in 250ml sodium chloride 0.9% over 60 minutes on day 1. Dose banded per CSCCN agreed bands. In patients with poor bone marrow reserves consider starting dose 55mg/m² with view to increase to 75mg/m² if well tolerated. Doses >190mg must be diluted in 500ml (max concentration 0.74mg/mL). Exfoliant - follow extravasation protocol."
      },
      {
        "drug_name": "Cyclophosphamide",
        "dose": 500.0,
        "dose_unit": "mg/m²",
        "route": "IV bolus",
        "days": [
          1
        ],
        "infusion_duration_hours": 0.167,
        "max_dose": null,
        "max_dose_unit": null,
        "notes": "500mg/m² IV bolus over 10 minutes on day 1. Dose banded per CSCCN agreed bands. Consider mesna for renal impairment. Reduce to 75% if CrCl 10-20ml/min; 50% if CrCl <10ml/min."
      }
    ],
    "dose_modifications": [
      {
        "condition": "Febrile neutropenia or neutrophil <0.5x10^9/L or platelets <50x10^9/L for >7 days",
        "drug_name": "Cyclophosphamide",
        "factor": 0.8,
        "notes": "Reduce all agents to 80% of original dose. If neutropenia/thrombocytopenia recurs despite dose reduction, further reduce to 50% or stop treatment."
      },
      {
        "condition": "Febrile neutropenia or neutrophil <0.5x10^9/L or platelets <50x10^9/L for >7 days",
        "drug_name": "Docetaxel",
        "factor": 0.8,
        "notes": "Reduce all agents to 80% of original dose."
      },
      {
        "condition": "Febrile neutropenia or neutrophil <0.5x10^9/L or platelets <50x10^9/L for >7 days",
        "drug_name": "Doxorubicin",
        "factor": 0.8,
        "notes": "Reduce all agents to 80% of original dose."
      },
      {
        "condition": "Hepatic impairment bilirubin 20-51 umol/L",
        "drug_name": "Doxorubicin",
        "factor": 0.5,
        "notes": "Give 50% of dose."
      },
      {
        "condition": "Hepatic impairment bilirubin 51-85 umol/L",
        "drug_name": "Doxorubicin",
        "factor": 0.25,
        "notes": "Give 25% of dose."
      },
      {
        "condition": "Hepatic impairment bilirubin >85 umol/L",
        "drug_name": "Doxorubicin",
        "factor": 0.0,
        "notes": "Omit doxorubicin."
      },
      {
        "condition": "Hepatic impairment AST 2-3x ULN",
        "drug_name": "Doxorubicin",
        "factor": 0.75,
        "notes": "Give 75% of dose."
      },
      {
        "condition": "Hepatic impairment AST >3x ULN",
        "drug_name": "Doxorubicin",
        "factor": 0.5,
        "notes": "Give 50% of dose."
      },
      {
        "condition": "Hepatic impairment: AST/ALT >=1.5x ULN and Alk Phos >=2.5x ULN",
        "drug_name": "Docetaxel",
        "factor": 0.75,
        "notes": "Give 75% of dose."
      },
      {
        "condition": "Hepatic impairment: bilirubin >ULN and/or AST/ALT >=3.5x ULN and Alk Phos >=6x ULN",
        "drug_name": "Docetaxel",
        "factor": 0.0,
        "notes": "Not recommended."
      },
      {
        "condition": "Renal impairment CrCl 10-20 ml/min",
        "drug_name": "Cyclophosphamide",
        "factor": 0.75,
        "notes": "Reduce to 75%. Consider mesna."
      },
      {
        "condition": "Renal impairment CrCl <10 ml/min",
        "drug_name": "Cyclophosphamide",
        "factor": 0.5,
        "notes": "Reduce to 50%. Consider mesna."
      },
      {
        "condition": "Peripheral neuropathy NCI-CTC Grade 3 or above",
        "drug_name": "Docetaxel",
        "factor": 0.8,
        "notes": "Dose reduction to 80% of original dose in the first instance."
      },
      {
        "condition": "NCI-CTC Grade 3 cutaneous toxicity on day 1 of cycle",
        "drug_name": "Docetaxel",
        "factor": 1.0,
        "notes": "Delay until resolves to NCI-CTC grade 1 or below. Subsequent doses reduced to 80% of original. Discontinue if no recovery after 2 weeks or NCI-CTC grade 4 cutaneous toxicity."
      },
      {
        "condition": "Cardiac failure",
        "drug_name": "Doxorubicin",
        "factor": 0.0,
        "notes": "Discontinue doxorubicin if cardiac failure develops."
      }
    ],
    "pre_medications": [
      "Dexamethasone 8mg twice daily oral starting day before docetaxel (day -1) for 3 days total (to prevent fluid retention and hypersensitivity). On occasions where pre-medication forgotten, give dexamethasone 20mg IV once only bolus.",
      "Ondansetron 8mg oral or IV 15-30 minutes before chemotherapy",
      "Ondansetron 8mg twice daily oral for 3 days starting evening of day 1 (take home)",
      "Metoclopramide 10mg three times daily when required oral (take home)",
      "G-CSF: filgrastim or bioequivalent 300mcg SC daily for 7 days from day 3, OR lenograstim or bioequivalent 263mcg SC daily for 7 days from day 3, OR pegfilgrastim or bioequivalent 6mg SC on day 2"
    ],
    "special_warnings": [
      "Doxorubicin: maximum cumulative lifetime dose is 450mg/m². Baseline LVEF measurement required especially in patients with cardiac history.",
      "Doxorubicin is a vesicant - follow extravasation guidelines. Discontinue if cardiac failure develops.",
      "Docetaxel: hypersensitivity reactions tend to occur with first or second infusion. Do not interrupt for minor symptoms (flushing, localised rash). Immediately discontinue for severe reactions (profound hypotension, bronchospasm, generalised erythema).",
      "Docetaxel-induced fluid retention can lead to weight gain - this is NOT a reason to alter doses.",
      "Excessive tearing/lacrimation related to cumulative docetaxel doses (median 400mg/m²) - treat with hypromellose 0.3% eye drops. If ocular irritation continues, reduce docetaxel to 80%.",
      "In patients with poor bone marrow reserves (extensive prior treatment, bone metastases, extensive skeletal radiation) consider starting docetaxel at 55mg/m² with view to increase to 75mg/m² if well tolerated.",
      "Growth factor (G-CSF) support mandatory.",
      "Mouthwashes per local/national mucositis policy.",
      "FBC, U&Es and LFTs prior to each cycle.",
      "Ensure adequate cardiac function before starting treatment. Baseline LVEF should be measured."
    ],
    "required_patient_fields": [
      "neutrophil_count",
      "platelet_count",
      "liver_function_tests",
      "creatinine_clearance",
      "lvef"
    ],
    "auc_dosing": null
  }
]